定义:  
- 向上造型:子类型的实例指向父类型的引用;  
- 向下造型:父类型的引用指向的实例,变更指向子类型的引用.(有时会涉及强转)  

---

向上造型的优劣性:  
- 可复用性;  
- 可扩展性;  
- 接口缩小;  

_(1)演示可复用性:_  
```java
public class App {  
    public void useSup(Sup sup) {  
        sup.method();  
    }  
    public static void main(String[] args) {  
        App app = new App();  
        app.useSup(new Sup());// out:sup  
        app.useSup(new Sub());// out:sub  
        app.useSup(new Inher());// out:inher  
    }  
}  
class Sup {  
    public void method() {  
        System.out.println("sup");  
    }  
}  
class Sub extends Sup {  
    public void method() {  
        System.out.println("sub");  
    }  
}  
class Inher extends Sub {  
    public void method() {  
        System.out.println("inher");  
    }  
}  
```  
_(2)演示可扩展性:_  
```java
public class App {  
    public void useSup(Sup sup) {  
        sup.method();  
    }  
    public static void main(String[] args) {  
        App app = new App();  
        app.useSup(new SubAnother()); // out:subAnother  
    }  
}  
class Sup {  
    public void method() {  
        System.out.println("sup");  
    }  
}  
class Sub extends Sup {  
    public void method() {  
        System.out.println("sub");  
    }  
}  
class Inher extends Sub {  
    public void method() {  
        System.out.println("inher");  
    }  
}  
class SubAnother extends Sup {  
    public void method() {  
        System.out.println("subAnother");  
    }  
}  
```  
_(3)演示接口缩小:_  
```java
package ocn.axy.locale;  
public class App {  
    public static void main(String[] args) {  
        Sup sup = new Sub();  
        sup.m1();  
        // sup.m2();// ERROR  
    }  
}  
class Sup {  
    public void m1() {  
        System.out.println("sup-m1");  
    }  
}  
class Sub extends Sup {  
    public void m1() {  
        System.out.println("sub-m1");  
    }  
    public void m2() {  
        System.out.println("sub-m2");  
    }  
}  
```  

---

向下造型和`RTTI`:  
`RTTI`定义:  
- 在运行期间对类型检查的行为叫做运行时类型识别,`RTTI`.  
- 在向下造型的过程中,编译器和虚拟机都会尽可能的进行类型检查.虚拟机的检查过程更为严格.  

_实际代码:_  
```java
public class App {  
    @SuppressWarnings("unused")  
    public static void main(String[] args) {  
        Sup sup = new Sub();  
        Sub sub = (Sub) sup; // valid  
        Object obj = sup;// valid  
        Random random = (Random) obj;// throws:ClassCastException  
    }  
}  
class Sup {}  
class Sub extends Sup {}  
```  
_反汇编验证:_  
```java
public class ocn.axy.locale.App {  
  public ocn.axy.locale.App();  
    Code:  
       0: aload_0  
       1: invokespecial #8                  // Method java/lang/Object."<init>":()V  
       4: return  

  public static void main(java.lang.String[]);  
    Code:  
       0: new           #16                 // class ocn/axy/locale/Sub  
       3: dup  
       4: invokespecial #18                 // Method ocn/axy/locale/Sub."<init>":()V
       7: astore_1  
       8: aload_1  
       9: checkcast     #16                 // class ocn/axy/locale/Sub  ==>>进行了转换检查
      12: astore_2  
      13: aload_1  
      14: astore_3  
      15: aload_3  
      16: checkcast     #19                 // class java/util/Random  ==>>进行了转换检查
      19: astore        4  
      21: return  
}  
```  
