___构造器`Constructor`在Java中是一种特殊的方法.___  

---

以下是对构造器的归纳:  
- 默认构造器`default-constructor`:  
  - 在类的定义中,若没有显式的定义类的构造器,编译器会给类插入一个无参的构造器.  
  - 内部的执行方法大概是:`super();`和`return;`,当然这两条语句中间会在必要的时候插入其他语句.  
- 对象的初始化:使用构造器(`new ClassDefined([params]);`)  
  - 涉及到全局属性的默认初始化机制;  
  - 在存在继承关系的时候,构造器会按照继承链条依次调用的.  
  - 涉及到`init-block`代码块的时候,是种很有趣的现象.  
- 构造器和`init-block`,`static-init-block`:  
  - 编译器将`init-block`的语句,插入到`super();`和`return;`语句中间.  
  - `static-init-block`和构造器无关,在类加载的时候就会执行;  
- 构造器和隐式参数:  
  - 构造器是一种特殊的Java方法;  
  - 其参数列表中,也是存在第一个隐式参数`this`的.  
- 构造器和继承:  
  - 继承关系中,构造器按照继承链依次向上调用,这是一种规则.  
  - 若类的构造器是`private`修饰的,该类不可被继承.  
  - 构造器内部不推荐调用多态方法,若必须这么做,应当调用`final`或之`private`方法.  

---

默认的构造器:  
- 未显式指定,编译器插入.  
- 指定有参构造器,但会指定,编译器不插入.  

_(1)编译器插入现象:_  
实际代码:  
```java
public class App {  
}  
```  
反汇编验证:  
```java
public class ocn.axy.abc.App {  
  public ocn.axy.abc.App();  
    Code:  
       0: aload_0  
       1: invokespecial #8                  // Method java/lang/Object."<init>":()V  
       4: return  
}  
```  
_(2)编译器不插入现象:_  
实际代码:  
```java
public class App {  
    public App(int param) {}  
}  
```  
反汇编验证:  
```java
public class ocn.axy.abc.App {  
  public ocn.axy.abc.App(int);  
    Code:  
       0: aload_0  
       1: invokespecial #8                  // Method java/lang/Object."<init>":()V  
       4: return  
}  
```  

---

初始化:  
构造器的作用:初始化类实例,即创建具体对象.  
- 在`Java`中,使用`new`关键字创建对象实例.  
- 对于类的属性,若不手动初始化,会配置默认值.  
- 在继承关系中,会依次执行继承链上的构造器.  
- `init-block`代码块,编译器会插入到构造器中.  

```java
public class App {  
    private int i;  
    private Object obj;  
    public static void main(String[] args) {  
        App app = new App();  
        System.out.println(app);// App [i=0, obj=null]  
    }  
    @Override  
    public String toString() {  
        return "App [i=" + i + ", obj=" + obj + "]";  
    }  
}  
```  

---

构造器和`init-block`代码块:  
`init-block`作用:提炼代码简洁度,放置可复用的初始化作业.  
- `init-block`,释义非静态初始化代码块.  
- 本质上就是构造器,在编译的时候,编译器会将`init-block`代码块的执行语句,插入到构造器内部,且是`super();`语句之后.  
- 即使存在多个构造器,编译器也会批量的插入.  

_实际代码:_  
```java
public class App {  
    {  
        System.out.println("init-block");  
    }  
    public App() {  
        System.out.println("default-init-function");  
    }  
    public App(int param) {  
        System.out.println("handler-init-function");  
    }  
}  
```  
_反汇编验证:_  
```java
public class ocn.axy.abc.App {  
  public ocn.axy.abc.App();  
    Code:  
       0: aload_0  
       1: invokespecial #8                  // Method java/lang/Object."<init>":()V ==>super();语句  
       4: getstatic     #10                 // Field java/lang/System.out:Ljava/io/PrintStream; ==>编译器插入  
       7: ldc           #16                 // String init-block  
       9: invokevirtual #18                 // Method java/io/PrintStream.println:(Ljava/lang/String;)V  
      12: getstatic     #10                 // Field java/lang/System.out:Ljava/io/PrintStream;  
      15: ldc           #24                 // String default-init-function  
      17: invokevirtual #18                 // Method java/io/PrintStream.println:(Ljava/lang/String;)V  
      20: return  

  public ocn.axy.abc.App(int);  
    Code:  
       0: aload_0  
       1: invokespecial #8                  // Method java/lang/Object."<init>":()V ==>super();语句  
       4: getstatic     #10                 // Field java/lang/System.out:Ljava/io/PrintStream; ==>编译器插入  
       7: ldc           #16                 // String init-block  
       9: invokevirtual #18                 // Method java/io/PrintStream.println:(Ljava/lang/String;)V  
      12: getstatic     #10                 // Field java/lang/System.out:Ljava/io/PrintStream;  
      15: ldc           #31                 // String handler-init-function  
      17: invokevirtual #18                 // Method java/io/PrintStream.println:(Ljava/lang/String;)V  
      20: return  
}  
```  

---

静态的`init-block`  
- `static-init-block`,是在类加载的时期执行的.  
- 该代码块只接受全局的静态变量.  

_实际代码:_  
```java
public class App {  
    static {  
        System.out.println("static-init-block");  
    }  
    public static void main(String[] args) throws ClassNotFoundException {  
        ClassLoader loader = Thread.currentThread().getContextClassLoader();  
        loader.loadClass(App.class.getName());  
    }  
}  
// console:static-init-block  
```  
_类加载器相关方法源码查阅:_  
```java
java.lang.ClassLoader.loadClass(String):  
  public Class<?> loadClass(String name) throws ClassNotFoundException {  
       return loadClass(name, false);  
   }  

java.lang.ClassLoader.loadClass(String, boolean):  
   protected Class<?> loadClass(String name, boolean resolve)  
       throws ClassNotFoundException  
   {  
       synchronized (getClassLoadingLock(name)) {  
           // First, check if the class has already been loaded  
           Class<?> c = findLoadedClass(name);  
```  

---

构造器和隐式参数:在构造器中是存在隐式参数`this`的.  
_实际代码:_  
```java
public class App {  
    public App() {}  
    public App(int num) {}  
}  
```  
_反汇编验证:_  
```java
{  
  public ocn.axy.abc.App();  
    descriptor: ()V  
    flags: ACC_PUBLIC  
    Code:  
      stack=1, locals=1, args_size=1  
         0: aload_0  
         1: invokespecial #8                  // Method java/lang/Object."<init>":()V  
         4: return  
      LineNumberTable:  
        line 3: 0  
      LocalVariableTable:  
        Start  Length  Slot  Name   Signature  
            0       5     0  this   Locn/axy/abc/App;  

  public ocn.axy.abc.App(int);  
    descriptor: (I)V  
    flags: ACC_PUBLIC  
    Code:  
      stack=1, locals=2, args_size=2  
         0: aload_0  
         1: invokespecial #8                  // Method java/lang/Object."<init>":()V  
         4: return  
      LineNumberTable:  
        line 4: 0  
        LocalVariableTable:  
          Start  Length  Slot  Name   Signature  
              0       5     0  this   Locn/axy/abc/App;  
              0       5     1   num   I  
  }  
```  

---

构造器和继承:  
- 构造器执行链:子类默认构造器的首行插入`super();`语句.  
- 不可继承类:若私有化唯一的默认构造器该类不可被继承.  
- 构造器配置:若是必须的,其内部推荐调用`final`或之`private`方法.  

_(1)构造器执行链条`super();`:_  
- 若存在继承关系,调用子类的构造器,内部会调用父类的构造器.  
- 简言之,在默认的构造器的首行,编译器会默认插入`super();`语句.  

实际代码:  
```java
public class App {  
    public static void main(String[] args) {  
        new InherSub();  
        // out : 1 2 3  
    }  
}  
class Sup {  
    public Sup() {  
        System.out.println(1);  
    }  
}  
class Sub extends Sup {  
    public Sub() {  
        System.out.println(2);  
    }  
}  
class InherSub extends Sub {  
    public InherSub() {  
        System.out.println(3);  
    }  
}  
```  
反汇编验证:  
```java
class ocn.axy.locale.InherSub extends ocn.axy.locale.Sub {  
  public ocn.axy.locale.InherSub();  
    Code:  
       0: aload_0  
       1: invokespecial #8                  // Method ocn/axy/locale/Sub."<init>":()V  ==>调用父类Sub  
       4: getstatic     #10                 // Field java/lang/System.out:Ljava/io/PrintStream;  
       7: iconst_3  
       8: invokevirtual #16                 // Method java/io/PrintStream.println:(I)V  
      11: return  
}  


class ocn.axy.locale.Sub extends ocn.axy.locale.Sup {  
  public ocn.axy.locale.Sub();  
    Code:  
       0: aload_0  
       1: invokespecial #8                  // Method ocn/axy/locale/Sup."<init>":()V  ==>调用父类Sup  
       4: getstatic     #10                 // Field java/lang/System.out:Ljava/io/PrintStream;  
       7: iconst_2  
       8: invokevirtual #16                 // Method java/io/PrintStream.println:(I)V  
      11: return  
}  


class ocn.axy.locale.Sup {  
  public ocn.axy.locale.Sup();  
    Code:  
       0: aload_0  
       1: invokespecial #8                  // Method java/lang/Object."<init>":()V  ==>调用父类Object  
       4: getstatic     #10                 // Field java/lang/System.out:Ljava/io/PrintStream;  
       7: iconst_1  
       8: invokevirtual #16                 // Method java/io/PrintStream.println:(I)V  
      11: return  
}  
```  
_(2)不可继承类:_  
根据构造器执行链的规则,假设类仅有一个构造器,且私有化,那么该类不可被继承!  
此种现象可部分实现`final`类的功能.  
```java
class Sup {  
    private Sup() {}  
}  
// Implicit super constructor Sup() is not visible for  
// default constructor. Must define an explicit constructor
class Sub extends Sup {} // ERROR  
```  
_(3)构造器内部的多态方法:_  
通常,构造器主要的任务是执行简单的初始化任务的.注意,要求简单的.  
若必须调用类的行为方法,一般推荐是调用`private`或者`final`方法.  
若在构造器内部调用重写的多态方法,执行过程无法保障,依据运行时实例.  
```java
public class App {  
    public static void main(String[] args) {  
        // 实际上在抽象父类的时候，预期的是输出：sup-<init>  
        new Sub();// out:sub-<init>  
    }  
}  
class Sup {  
    public Sup() {  
        method();  
    }  
    public void method() {  
        System.out.println("sup-<init>");  
    }  
}  
class Sub extends Sup {  
    public Sub() {}  
    @Override  
    public void method() {  
        System.out.println("sub-<init>");  
    }  
}  
```  
