方法重写:  
- 重写规则:两同两小一大  
- 桥方法`JDK5`  
- 非强制的注解`@Override`  

伪装重写:  
- 伪装重写`private`方法;  
- 伪装重写全局域;  
- 伪装重写`statis`方法;  

---

重写的规则:  
- 方法签名必须保持一致!  
- 子类访问权限 `>=` 父类访问权限;  
- 子类抛出异常 `<=` 父类抛出异常;  
- 子类返回类型 `<=` 父类返回类型;  

可总结为两同(方法名+参数列表)两小(返回类型+抛出异常)一大(访问权限).  

重写的限制:  
- 不可重写父类的`private`,`static`方法;  
- 不可重写从父类继承来的非`private`全局属性;  

```java
class Sup {  
    Object method(int num) throws Throwable {  
        return new Object();  
    }  
}  
class Sub extends Sup {  
    @Override  
    protected Random method(int num) throws Exception {  
        return new Random();  
    }  
}  
```  

---

协变返回类型JDK5:  
- 在JDK5之前的版本,重写方法的返回类型,必须和父类的保持一致.  
- JDK5开始,添加了协变返回类型技术,有时也称作桥方法,支持重写方法返回类型向下扩展.  
- 简言之,协变返回类型就是:重写方法返回类型<=父类方法的返回类型.  

_实际代码:_  
```java
class Sup {  
    public Object m1() {  
        return new Object();  
    }  
}  
class Sub extends Sup {  
    @Override  
    public Random m1() {  
        return new Random();  
    }  
}  
```  
_反汇编验证:_  
```java
class ocn.axy.locale.Sub extends ocn.axy.locale.Sup {  
  ocn.axy.locale.Sub();  
    Code:  
       0: aload_0  
       1: invokespecial #8                  // Method ocn/axy/locale/Sup."<init>":()V  
       4: return  

  public java.util.Random m1();  
    Code:  
       0: new           #16                 // class java/util/Random  
       3: dup  
       4: invokespecial #18                 // Method java/util/Random."<init>":()V  
       7: areturn  

  public java.lang.Object m1();             // 桥方法|协变返回类型;  
    Code:  
       0: aload_0  
       1: invokevirtual #20                 // Method m1:()Ljava/util/Random;   ==>支持多态,调用子类重写方法  
       4: areturn  
}  
```  

---

非必要标准的注解JDK5:  
- 注解`@Override`主要标记方法是重写父类的方法.  
- 此注解没有强制性约束,即使没有该注解,满足重写规则,方法也会被定性为重写.  
- 注意:为了编码的规范和可阅读性,应当使用该注解标记重写方法!  

_实际代码(借用桥方法验证):_  
```java
class Sup {  
    public Object method() {  
        return new Object();  
    }  
}  
class Sub extends Sup {  
    public Random method() {  
        return new Random();  
    }  
}  
```  
_反汇编验证:_  
```java
class ocn.axy.locale.Sub extends ocn.axy.locale.Sup {  
  ocn.axy.locale.Sub();  
    Code:  
       0: aload_0  
       1: invokespecial #8                  // Method ocn/axy/locale/Sup."<init>":()V  
       4: return  

  public java.util.Random method();  
    Code:  
       0: new           #16                 // class java/util/Random  
       3: dup  
       4: invokespecial #18                 // Method java/util/Random."<init>":()V  
       7: areturn  

  public java.lang.Object method();  
    Code:  
       0: aload_0  
       1: invokevirtual #20                 // Method method:()Ljava/util/Random;  
       4: areturn  
}  
```  

---

类的清理作业:  
- 在继承关系中,若涉及到清理作业的方法,注意是非`finalize`方法,假设是`dispose`方法.  
- 若子类重写父类的`dispose`方法,在重写方法的首行应调用`super.dispose();`语句.  
- 否则父类的清理工作不会执行的.  

_反例演示:_  
```java
public class App {  
    public static void main(String[] args) {  
        Sup sup = new Sub();  
        sup.dispose();  
    }  
}  
class Sup {  
    public void dispose() {  
        System.out.println("sup-start-dispose");  
    }  
}  
class Sub extends Sup {  
    @Override  
    public void dispose() {  
        // super.dispose();//should-called  
        System.out.println("sub-start-dispose");  
    }  
}  
```  

---

伪装重写:  
_(1)伪装重写`private`方法:_  
若父类的方法是私有的,是不可被重写的!---face  
实际代码(伪装重写`private`)方法:  
```java
class Sup {  
    private Object method() {  
        return new Object();  
    }  
}  
class Sub extends Sup {  
    public Random method() {  
        return new Random();  
    }  
}  
```  
反汇编查看是否产生桥方法:  
```java
class ocn.axy.locale.Sub extends ocn.axy.locale.Sup {  
  ocn.axy.locale.Sub();  
    Code:  
       0: aload_0  
       1: invokespecial #8                  // Method ocn/axy/locale/Sup."<init>":()V  
       4: return  

  public java.util.Random method();  
    Code:  
       0: new           #16                 // class java/util/Random  
       3: dup  
       4: invokespecial #18                 // Method java/util/Random."<init>":()V  
       7: areturn  
}  
```  
_(2)伪装重写全局域:_  
- 父类的全局属性可以被继承,但不可能被重写,即使定义同类型,同标识的全局变量.  
- 即使使用了向上造型,实际调用的也是指向实际对象的指针.  

```java
public class App {  
    public static void main(String[] args) {  
        Sub sub = new Sub();// out:32  
        System.out.println(sub.num);  
        Sub sup = new Sub();  
        System.out.println(sup.num);// out:32  
    }  
}  
class Sup {  
    int num;  
}  
class Sub extends Sup {  
    int num = 32;  
}  
```  
_(3)伪装重写`static`方法:_  
- 继承机制中,子类可以调用父类的静态方法;  
- 子类可以定义和父类一样方法签名的静态方法,但这不是重写!  
- 子类若定义和父类静态方法一样方法签名的非`static`方法是非法的!  

```java
public class App {  
    public static void main(String[] args) {  
        Sub.m1(); // out:sub-m1  
        // 继承机制，可以调用父类的静态方法。  
        Sub.m3();// out:sup-m3  
    }  
}  
class Sup {  
    public static void m1() {  
        System.out.println("sup-m1");  
    }  
    public static void m2() {  
        System.out.println("sup-m2");  
    }  
    public static void m3() {  
        System.out.println("sup-m3");  
    }  
}  
class Sub extends Sup {  
    // 事实上不是重写，但定义和父类一样方法签名的静态方法是允许的。  
    public static void m1() {  
        System.out.println("sub-m1");  
    }  
    // 父类的静态方法，不支持重写，编译报错。  
    // public void m2() { // ERROR  
    // System.out.println("sub-m2");  
    // }  
}  
```  
