断言机制:  
1. 断言机制是类加载器和JVM的行为.  
1. 断言使用关键点:`assert 条件;`,`assert 条件:表达式;`,`AssertionError`.  
1. 断言默认关闭的,可开启:`java -ea/-esa`或之`ClassLoader#...`.  
1. 断言适用场景:前置条件+文档注释替换.  

---

断言的生存环境:  
- 默认情况下,断言功能是被禁用的.  
- 断言功能是否可用,是由类加载器或之虚拟机决定的.  
- 若断言被禁用,类加载器或之虚拟机在加载字节码的时候,会选择性的跳过断言代码.  
  从用户的角度,好似涉及到断言的代码都被移除了.从而优化了应用的测试和部署.  

---

断言的语法:  
- `assert 条件;`  
- `assert 条件:表达式;`  

在使用`assert`语句的时候,编译器会默认插入`AssertionError`的`<init>`指令.该对象主要负责将断言的校验结果保存抛出.  
以下进行验证:  
_实际代码:_  
```java
package ocn.axy.run;
public class App {
	public static void main(String[] args) {
		int num = 32;;
		assert num < 0;
		System.out.println(num);
	}
}
```  
_反汇编验证:_  
```java
public static void main(java.lang.String[]);
  Code:
     0: bipush        32
     2: istore_1
     3: getstatic     #16                 // Field $assertionsDisabled:Z
     6: ifne          21
     9: iload_1
    10: iflt          21
    13: new           #28                 // class java/lang/AssertionError  ==>>执行new指令
    16: dup
    17: invokespecial #30                 // Method java/lang/AssertionError."<init>":()V  ==>>初始化AssertionError
    20: athrow   
    21: getstatic     #31                 // Field java/lang/System.out:Ljava/io/PrintStream;
    24: iload_1
    25: invokevirtual #37                 // Method java/io/PrintStream.println:(I)V
    28: return
```  

---

断言功能默认是关闭的,有两种开启方式,一个是`java`指令,一个是通过类加载器`ClassLoader`.  
_java指令的参考:_  
对于`-ea`和`-esa`,前者针对的是类加载器的范围,后者针对的是JVM的范围.  
因为有些类是JVM负责加载的.  
```shell
用法: java [-options] class [args...]
           (执行类)
   或  java [-options] -jar jarfile [args...]
           (执行 jar 文件)
其中选项包括:
-ea[:<packagename>...|:<classname>]
-enableassertions[:<packagename>...|:<classname>]
              按指定的粒度启用断言
-da[:<packagename>...|:<classname>]
-disableassertions[:<packagename>...|:<classname>]
              禁用具有指定粒度的断言
-esa | -enablesystemassertions
              启用系统断言
-dsa | -disablesystemassertions
              禁用系统断言
```  
_`ClassLoader`:_  
```java
java.lang.ClassLoader.setDefaultAssertionStatus(boolean)  // 设置该加载器负责类的所有默认断言状态
java.lang.ClassLoader.setPackageAssertionStatus(String, boolean)  // 设置指定包内所有类的断言状态
java.lang.ClassLoader.setClassAssertionStatus(String, boolean)  // 设置指定类及其内部类的断言状态
java.lang.ClassLoader.clearAssertionStatus()  // 清空断言状态  
```  

---

断言适用场景:前置条件+文档注释  
_前置条件:_  
```java
package ocn.axy.run;
public class App {
	public void function(int num) {
		assert num > 0;// 前置条件
		// to-do
	}
}
```  
_文档注释替换:_  
```java
package ocn.axy.run;
public class App {
	public void m1(int num) {
		if (num % 3 == 0) {
			// to-do
		} else if (num % 3 == 1) {
			// to-do
		} else {
			// num%3==2 --->handler
			// to-do
		}
	}
	public void m2(int num) {
		if (num % 3 == 0) {
			// to-do
		} else if (num % 3 == 1) {
			// to-do
		} else {
			assert num % 3 == 2;// 文档注释替换
			// to-do
		}
	}
}
```  
