缺省默认机制:  
- `class:::final`  
- `constructor:::private`  
- `Generic.T:::public final static`  
- 每个枚举类都强制插入`values()`方法.  

以以下枚举类实例代码为参照点反汇编:  
```java
package ocn.axy.run;
enum Info {
	A, B, C;
}
```  

---

类修饰符强制使用`final`修饰符:  
```java
final class ocn.axy.run.Info extends java.lang.Enum<ocn.axy.run.Info>
  minor version: 0
  major version: 52
  flags: ACC_FINAL, ACC_SUPER, ACC_ENUM
```  

---

构造器强制使用`private`修饰符:  
```java
Compiled from "Info.java"
final class ocn.axy.run.Info extends java.lang.Enum<ocn.axy.run.Info> {
  public static final ocn.axy.run.Info A;
  public static final ocn.axy.run.Info B;
  public static final ocn.axy.run.Info C;
  private static final ocn.axy.run.Info[] ENUM$VALUES;
  static {};
  private ocn.axy.run.Info(java.lang.String, int);
  public static ocn.axy.run.Info[] values();
  public static ocn.axy.run.Info valueOf(java.lang.String);
}
```  

---

类型变量类属性强制使用`public final static`修饰:  
```java
Compiled from "Info.java"
final class ocn.axy.run.Info extends java.lang.Enum<ocn.axy.run.Info> {
  public static final ocn.axy.run.Info A;

  public static final ocn.axy.run.Info B;

  public static final ocn.axy.run.Info C;
```  

---

强制给每个枚举类插入`values()`方法:  
```java
public static ocn.axy.run.Info[] values();
  Code:
     0: getstatic     #27                 // Field ENUM$VALUES:[Locn/axy/run/Info;
     3: dup
     4: astore_0
     5: iconst_0
     6: aload_0
     7: arraylength
     8: dup
     9: istore_1
    10: anewarray     #1                  // class ocn/axy/run/Info
    13: dup
    14: astore_2
    15: iconst_0
    16: iload_1
    17: invokestatic  #35                 // Method java/lang/System.arraycopy:(Ljava/lang/Object;ILjava/lang/Object;II)V
    20: aload_2
    21: areturn
```  
